LICENSE
MANIFEST.in
NOTICE
setup.py
boltkit/__init__.py
boltkit/addressing.py
boltkit/bytetools.py
boltkit/cluster.py
boltkit/config.py
boltkit/controller.py
boltkit/driver.py
boltkit/multicluster.py
boltkit/packstream.py
boltkit/proxy.py
boltkit/runner.py
boltkit/server.py
boltkit/watcher.py
boltkit.egg-info/PKG-INFO
boltkit.egg-info/SOURCES.txt
boltkit.egg-info/dependency_links.txt
boltkit.egg-info/entry_points.txt
boltkit.egg-info/requires.txt
boltkit.egg-info/top_level.txt